[
  {
    "desc": "一只白羊 - 说书",
    "people": "123.6"
  },
  {
    "desc": "郭德纲、于谦 - 我家的狗丢了 (相声)",
    "people": "211.1"
  },
  {
    "desc": "阿萨Aza - 说书先生",
    "people": "1312.9"
  },
  {
    "desc": "郝喜宁 - 陕北说书 (爱上三哥哥)",
    "people": "171.1"
  },
  {
    "desc": "熊竹英、游戏科学、8182Audio - 黄风起兮",
    "people": "1315.3"
  },
  {
    "desc": "评书大全 - 第119集 黑虎传",
    "people": "234.1"
  },
  {
    "desc": "评书大全 - 第171集 黑虎传",
    "people": "241.7"
  },
  {
    "desc": "最新相声评书 - 吕四娘刺雍正_19~1",
    "people": "1824.4"
  },
  {
    "desc": "老九门 - 老九门 92 诡异长沙城",
    "people": "1844.7"
  },
  {
    "desc": "最新相声评书 - 第9集",
    "people": "1313.3"
  },
  {
    "desc": "最新相声评书 - 第34集",
    "people": "1313.8"
  },
  {
    "desc": "最新相声评书 - 第51集",
    "people": "1313.2"
  },
  {
    "desc": "刘兰芳 - 岳飞传156 (评书版)",
    "people": "283.3"
  },
  {
    "desc": "袁阔成 - 【三国演义】第241回-陆伯言大火烧连营 (评书)",
    "people": "2945.7"
  },
  {
    "desc": "陈功、李伯清 - 师徒贺新春 (散打评书) (Live)",
    "people": "112.1"
  },
  {
    "desc": "樊宁 - 评书-醒木有声",
    "people": "133.6"
  },
  {
    "desc": "闻人听書_、魏楚沅 - 评书",
    "people": "134.6"
  },
  {
    "desc": "评书大全 - 五代十国风云录2 十国篇 第31集",
    "people": "223.1"
  },
  {
    "desc": "评书大全 - 第181集 黑虎传",
    "people": "241.6"
  },
  {
    "desc": "评书大全 - 第146集 黑虎传",
    "people": "2345.5"
  },
  {
    "desc": "评书大全 - 第116集 黑虎传",
    "people": "2324.4"
  },
  {
    "desc": "粤语评书 - 111",
    "people": "235.4"
  },
  {
    "desc": "刘兰芳 - 刘岳飞传121 (评书版)",
    "people": "285.1"
  },
  {
    "desc": "刘兰芳 - 岳飞传152 (评书版)",
    "people": "2815.5"
  },
  {
    "desc": "A[cuo] - 李伯清散打评书 (爱情与恋爱)",
    "people": "1413.5"
  },
  {
    "desc": "相声评书精选 - 汕头车站",
    "people": "141.1"
  },
  {
    "desc": "评书 - 方言四川",
    "people": "191.7"
  },
  {
    "desc": "薛振华 - 评书 (动画《万古最强宗》原声音乐)",
    "people": "115.5"
  },
  {
    "desc": "张悦楷 - 【飞狐外传】176回 (评书)",
    "people": "245.2"
  },
  {
    "desc": "苗霖66 - 评书",
    "people": "132.2"
  },
  {"desc": "百年经典", "people": "8309.2万"},
  {"desc": "速听郭德纲语录|老郭有新番第一季精彩集锦", "people": "160964万"},
  {"desc": "苏州评弹经典选段", "people": "223万"},
  {"desc": "昆曲名家名段精选", "people": "79.3万"},
  {"desc": "游园惊梦", "people": "4988.9万"},
  {"desc": "二人转传统戏合集", "people": "2354.5万"}
]