[
    {
        "desc": "王玥波评书专场-《聊斋志异》（全网最全）",
        "people": "69.7万"
    },
    {
        "desc": "王玥波评书专场-《兴唐扫北征东征西》",
        "people": "7.9万"
    },
    {
        "desc": "单田芳评书之《燕王扫北》",
        "people": "38.3万"
    },
    {
        "desc": "王玥波评书专场-《侠义英雄传》",
        "people": "1.4万"
    },
    {
        "desc": "看小说必备古风歌曲",
        "people": "275.7万"
    },
    {
        "desc": "单田芳评书『平原枪声』",
        "people": "7486"
    },
    {
        "desc": "王玥波评书专场-《雍正剑侠图》第一部",
        "people": "8.0万"
    },
    {
        "desc": "古风音乐，动漫二次元原耽",
        "people": "107.4万"
    },
    {
        "desc": "王玥波评书专场-《君臣斗》",
        "people": "4.1万"
    },
    {
        "desc": "古风合集【一个人，一座城，一生心疼】",
        "people": "387.0万"
    },
    {
        "desc": "超好听的宝藏古风歌曲",
        "people": "571.2万"
    },
    {
        "desc": "『单田芳评书』隋唐演义",
        "people": "3.1万"
    },
    {
        "desc": "王玥波评书专场-《雍正剑侠图》第三部",
        "people": "5.3万"
    },
    {
        "desc": "喊麦 ｜音乐中的评书",
        "people": "90"
    },
    {
        "desc": "闻人听書全部歌曲",
        "people": "2910"
    },
    {
        "desc": "粤语评书：杨门女将后传-林劲（粤语讲古）",
        "people": "1.3万"
    },
    {
        "desc": "逍遥令孤 《评书 三国演义》",
        "people": "3651"
    },
    {
        "desc": "全网百听不厌的抖音古风歌曲",
        "people": "17.5万"
    },
    {
        "desc": "粤语评书：金陵神探风流梦（昙花梦）-林劲",
        "people": "2032"
    },
    {
        "desc": "粤语评书：佢叫神算铁嘴张-林劲（粤语讲古）",
        "people": "2.4万"
    },
    {
        "desc": "王玥波评书专场-《红楼十二钗》",
        "people": "1181"
    },
    {
        "desc": "粤语评书：都市危情-林劲（粤语讲古）",
        "people": "6778"
    },
    {
        "desc": "粤语评书：杨家将-张悦谐（粤语讲古）",
        "people": "2.0万"
    },
    {
        "desc": "王玥波评书专场-《宋金刚押宝》",
        "people": "1.5万"
    },
    {
        "desc": "粤语评书：绝代双骄-郑达（粤语讲古）",
        "people": "1.7万"
    },
    {
        "desc": "粤语评书：狄青演义-林劲（粤语讲古）",
        "people": "2.1万"
    },
    {
        "desc": "粤语评书：隋唐演义-张悦楷（粤语讲古）",
        "people": "21.4万"
    },
    {
        "desc": "粤语评书：三侠五义-林兆明（粤语讲古）",
        "people": "11.2万"
    },
    {
        "desc": "粤语评书：包公端州传奇（粤语评书）",
        "people": "1780"
    },
    {
        "desc": "粤语评书：济公传-林兆明（粤语讲古）",
        "people": "14.7万"
    }
]